alibabacloud_cloudfw20171207/__init__.py
alibabacloud_cloudfw20171207/client.py
alibabacloud_cloudfw20171207/models/__init__.py
alibabacloud_cloudfw20171207/models/_add_acl_backup_data_request.py
alibabacloud_cloudfw20171207/models/_add_acl_backup_data_response.py
alibabacloud_cloudfw20171207/models/_add_acl_backup_data_response_body.py
alibabacloud_cloudfw20171207/models/_add_address_book_request.py
alibabacloud_cloudfw20171207/models/_add_address_book_response.py
alibabacloud_cloudfw20171207/models/_add_address_book_response_body.py
alibabacloud_cloudfw20171207/models/_add_control_policy_request.py
alibabacloud_cloudfw20171207/models/_add_control_policy_response.py
alibabacloud_cloudfw20171207/models/_add_control_policy_response_body.py
alibabacloud_cloudfw20171207/models/_add_dns_firewall_policy_request.py
alibabacloud_cloudfw20171207/models/_add_dns_firewall_policy_response.py
alibabacloud_cloudfw20171207/models/_add_dns_firewall_policy_response_body.py
alibabacloud_cloudfw20171207/models/_add_domain_resolve_realtime_task_request.py
alibabacloud_cloudfw20171207/models/_add_domain_resolve_realtime_task_response.py
alibabacloud_cloudfw20171207/models/_add_domain_resolve_realtime_task_response_body.py
alibabacloud_cloudfw20171207/models/_add_instance_members_request.py
alibabacloud_cloudfw20171207/models/_add_instance_members_response.py
alibabacloud_cloudfw20171207/models/_add_instance_members_response_body.py
alibabacloud_cloudfw20171207/models/_add_private_dns_domain_name_request.py
alibabacloud_cloudfw20171207/models/_add_private_dns_domain_name_response.py
alibabacloud_cloudfw20171207/models/_add_private_dns_domain_name_response_body.py
alibabacloud_cloudfw20171207/models/_batch_copy_vpc_firewall_control_policy_request.py
alibabacloud_cloudfw20171207/models/_batch_copy_vpc_firewall_control_policy_response.py
alibabacloud_cloudfw20171207/models/_batch_copy_vpc_firewall_control_policy_response_body.py
alibabacloud_cloudfw20171207-7.5.0.dist-info/LICENSE
alibabacloud_cloudfw20171207-7.5.0.dist-info/METADATA
alibabacloud_cloudfw20171207-7.5.0.dist-info/WHEEL
alibabacloud_cloudfw20171207-7.5.0.dist-info/top_level.txt
alibabacloud_cloudfw20171207-7.5.0.dist-info/RECORD
